LICENSE
README.md
pyproject.toml
setup.py
zmq_ops/__init__.py
zmq_ops/libzmq_ops.so
zmq_ops/tensor_array_pb2.py
zmq_ops/zmq_ops.py
zmq_ops.egg-info/PKG-INFO
zmq_ops.egg-info/SOURCES.txt
zmq_ops.egg-info/dependency_links.txt
zmq_ops.egg-info/not-zip-safe
zmq_ops.egg-info/requires.txt
zmq_ops.egg-info/top_level.txt