Metadata-Version: 2.1
Name: zmq-ops
Version: 0.4.0
Summary: UNKNOWN
Home-page: UNKNOWN
Author: Vino Wan
Author-email: vinowan@tencent.com
License: UNKNOWN
Platform: UNKNOWN
